Metadata-Version: 2.1
Name: topsis-101703289-khushnuma
Version: 1.0.0
Summary: A Python package implementing TOPSIS technique.
Home-page: https://github.com/khushgrover/topsis-python
Author: Khushnuma Grover
Author-email: khushgrover16@gmail.com
License: MIT
Platform: UNKNOWN
Classifier: License :: OSI Approved :: MIT License
Classifier: Programming Language :: Python :: 3
Classifier: Programming Language :: Python :: 3.7
Requires-Dist: scipy
Requires-Dist: tabulate
Requires-Dist: numpy
Requires-Dist: pandas
